SciAssist/__init__.py
SciAssist/test.py
SciAssist/train.py
SciAssist/bin/__init__.py
SciAssist/bin/__pycache__/__init__.cpython-38.pyc
SciAssist/bin/doc2json/LICENSE
SciAssist/bin/doc2json/__init__.py
SciAssist/bin/doc2json/setup.py
SciAssist/bin/doc2json/__pycache__/__init__.cpython-38.pyc
SciAssist/bin/doc2json/doc2json/__init__.py
SciAssist/bin/doc2json/doc2json/config.py
SciAssist/bin/doc2json/doc2json/s2orc.py
SciAssist/bin/doc2json/doc2json/__pycache__/__init__.cpython-38.pyc
SciAssist/bin/doc2json/doc2json/__pycache__/config.cpython-38.pyc
SciAssist/bin/doc2json/doc2json/__pycache__/s2orc.cpython-38.pyc
SciAssist/bin/doc2json/doc2json/grobid2json/__init__.py
SciAssist/bin/doc2json/doc2json/grobid2json/pdf_to_tei.py
SciAssist/bin/doc2json/doc2json/grobid2json/process_pdf.py
SciAssist/bin/doc2json/doc2json/grobid2json/tei_to_json.py
SciAssist/bin/doc2json/doc2json/grobid2json/__pycache__/__init__.cpython-38.pyc
SciAssist/bin/doc2json/doc2json/grobid2json/__pycache__/process_pdf.cpython-38.p
SciAssist/bin/doc2json/doc2json/grobid2json/__pycache__/tei_to_json.cpython-38.p
SciAssist/bin/doc2json/doc2json/grobid2json/grobid/Readme.md
SciAssist/bin/doc2json/doc2json/grobid2json/grobid/__init__.py
SciAssist/bin/doc2json/doc2json/grobid2json/grobid/client.py
SciAssist/bin/doc2json/doc2json/grobid2json/grobid/config.yaml
SciAssist/bin/doc2json/doc2json/grobid2json/grobid/grobid.properties
SciAssist/bin/doc2json/doc2json/grobid2json/grobid/grobid_client.py
SciAssist/bin/doc2json/doc2json/grobid2json/grobid/__pycache__/__init__.cpython-
SciAssist/bin/doc2json/doc2json/grobid2json/grobid/__pycache__/client.cpython-38
SciAssist/bin/doc2json/doc2json/grobid2json/grobid/__pycache__/grobid_client.cpy
SciAssist/bin/doc2json/doc2json/utils/__init__.py
SciAssist/bin/doc2json/doc2json/utils/citation_util.py
SciAssist/bin/doc2json/doc2json/utils/grobid_util.py
SciAssist/bin/doc2json/doc2json/utils/latex_util.py
SciAssist/bin/doc2json/doc2json/utils/refspan_util.py
SciAssist-0.1.4.dist-info/LICENSE
SciAssist-0.1.4.dist-info/METADATA
SciAssist-0.1.4.dist-info/WHEEL
SciAssist-0.1.4.dist-info/entry_points.txt
SciAssist-0.1.4.dist-info/top_level.txt
SciAssist-0.1.4.dist-info/RECORD
