Metadata-Version: 2.1
Name: SciAssist
Version: 0.1.4
Summary: A toolkit for Scientific Document Processing
Author-email: WING-NUS <dingyixi@hotmail.com>
Maintainer-email: Yixi Ding <dingyixi@hotmail.com>
License: Attribution-NonCommercial-ShareAlike 4.0 International
Project-URL: Homepage, https://github.com/WING-NUS/SciAssist
Project-URL: Bug Tracker, https://github.com/WING-NUS/SciAssist/issues
Classifier: Programming Language :: Python :: 3
Classifier: License :: Free for non-commercial use
Classifier: Operating System :: POSIX :: Linux
Requires-Python: >=3.8
License-File: LICENSE
Requires-Dist: beautifulsoup4 ~=4.9.0
Requires-Dist: chardet ~=3.0.4
Requires-Dist: datasets ~=2.15.0
Requires-Dist: hydra-core >=1.1.0
Requires-Dist: lxml
Requires-Dist: matplotlib ~=3.5.1
Requires-Dist: nltk ~=3.7
Requires-Dist: numpy
Requires-Dist: omegaconf ~=2.2.2
Requires-Dist: PyPDF2 ~=2.10.7
Requires-Dist: python-magic ~=0.4.18
Requires-Dist: pytorch-lightning ~=2.0.4
Requires-Dist: requests ~=2.22.0
Requires-Dist: rich ~=12.4.4
Requires-Dist: seaborn ~=0.11.2
Requires-Dist: setuptools >=61.0
Requires-Dist: torch >=1.12.0
Requires-Dist: torchmetrics ==0.11.4
Requires-Dist: transformers ~=4.30.2
Requires-Dist: wandb ~=0.12.19
Requires-Dist: pdfminer.six
Requires-Dist: pandas ~=1.4.3
Requires-Dist: pytorch-crf
Requires-Dist: torchcrf
Requires-Dist: sacremoses
Requires-Dist: seqeval
Requires-Dist: pytest ~=7.4.3
